{
  "legislative_session": "2025-2026",
  "identifier": "S1521",
  "title": "Allows retired state police officers to serve as police officers for local police departments without diminution of retirement benefits",
  "from_organization": "~{\"classification\": \"upper\"}",
  "classification": [
    "bill"
  ],
  "subject": [],
  "abstracts": [
    {
      "note": "",
      "abstract": "Allows retired state police officers to serve as police officers for local police departments without diminution of retirement benefits; empowers the superintendent of state police to approve such service."
    }
  ],
  "other_titles": [],
  "other_identifiers": [],
  "actions": [
    {
      "description": "REFERRED TO CIVIL SERVICE AND PENSIONS",
      "date": "2025-01-10",
      "organization_id": "~{\"classification\": \"upper\"}",
      "classification": [
        "referral-committee"
      ],
      "related_entities": []
    }
  ],
  "sponsorships": [
    {
      "name": "Thomas F. O'Mara",
      "classification": "primary",
      "entity_type": "person",
      "primary": true,
      "person_id": "~{\"name\": \"Thomas F. O'Mara\"}",
      "organization_id": null
    }
  ],
  "related_bills": [
    {
      "identifier": "A 6447",
      "legislative_session": "2025-2026",
      "relation_type": "companion"
    },
    {
      "identifier": "A 6447",
      "legislative_session": "2025-2026",
      "relation_type": "companion"
    },
    {
      "identifier": "S 2180",
      "legislative_session": "2023-2024",
      "relation_type": "prior-session"
    },
    {
      "identifier": "S 5499",
      "legislative_session": "2021-2022",
      "relation_type": "prior-session"
    },
    {
      "identifier": "S 1881",
      "legislative_session": "2019-2020",
      "relation_type": "prior-session"
    },
    {
      "identifier": "S 8950",
      "legislative_session": "2017-2018",
      "relation_type": "prior-session"
    }
  ],
  "versions": [
    {
      "note": "S1521",
      "links": [
        {
          "url": "http://assembly.state.ny.us/leg/?sh=printbill&bn=S1521&term=2025&Text=Y",
          "media_type": "text/html"
        },
        {
          "url": "http://legislation.nysenate.gov/pdf/bills/2025/S1521",
          "media_type": "application/pdf"
        }
      ],
      "date": "",
      "classification": ""
    }
  ],
  "documents": [],
  "citations": [
    {
      "publication": "New York Laws",
      "citation": "RSS \u00a7 211",
      "citation_type": "proposed",
      "effective": null,
      "expires": null,
      "url": "https://www.nysenate.gov/legislation/laws/RSS/"
    },
    {
      "publication": "New York Laws",
      "citation": "RSS \u00a7 212",
      "citation_type": "proposed",
      "effective": null,
      "expires": null,
      "url": "https://www.nysenate.gov/legislation/laws/RSS/"
    }
  ],
  "sources": [
    {
      "url": "https://legislation.nysenate.gov/api/3/bills/2025-2026/S1521?summary=&detail=",
      "note": ""
    },
    {
      "url": "http://www.nysenate.gov/legislation/bills/2025/S1521",
      "note": ""
    },
    {
      "url": "https://nyassembly.gov/leg/?bn=S01521&term=2025",
      "note": ""
    }
  ],
  "extras": {},
  "jurisdiction": {
    "id": "ocd-jurisdiction/country:us/state:ny/government",
    "name": "New York",
    "classification": "state",
    "division_id": "ocd-division/country:us/state:ny"
  },
  "scraped_at": "2025-08-05T18:56:51+00:00",
  "_id": "f2858908-722d-11f0-acc8-8e31291036f2"
}