{
  "legislative_session": "2025-2026",
  "identifier": "S4299",
  "title": "Authorizes the care and treatment of injured employees by duly licensed or certified acupuncturists under the workers' compensation program",
  "from_organization": "~{\"classification\": \"upper\"}",
  "classification": [
    "bill"
  ],
  "subject": [],
  "abstracts": [
    {
      "note": "",
      "abstract": "Authorizes the care and treatment of injured employees by licensed or certified acupuncturists under the workers' compensation program."
    }
  ],
  "other_titles": [],
  "other_identifiers": [],
  "actions": [
    {
      "description": "REFERRED TO LABOR",
      "date": "2025-02-03",
      "organization_id": "~{\"classification\": \"upper\"}",
      "classification": [
        "referral-committee"
      ],
      "related_entities": []
    }
  ],
  "sponsorships": [
    {
      "name": "Kevin S. Parker",
      "classification": "primary",
      "entity_type": "person",
      "primary": true,
      "person_id": "~{\"name\": \"Kevin S. Parker\"}",
      "organization_id": null
    }
  ],
  "related_bills": [
    {
      "identifier": "S 6775",
      "legislative_session": "2023-2024",
      "relation_type": "prior-session"
    },
    {
      "identifier": "S 5288",
      "legislative_session": "2021-2022",
      "relation_type": "prior-session"
    },
    {
      "identifier": "S 4547",
      "legislative_session": "2019-2020",
      "relation_type": "prior-session"
    },
    {
      "identifier": "S 3434",
      "legislative_session": "2017-2018",
      "relation_type": "prior-session"
    },
    {
      "identifier": "S 1490",
      "legislative_session": "2015-2016",
      "relation_type": "prior-session"
    },
    {
      "identifier": "S 803",
      "legislative_session": "2013-2014",
      "relation_type": "prior-session"
    },
    {
      "identifier": "S 7397",
      "legislative_session": "2011-2012",
      "relation_type": "prior-session"
    }
  ],
  "versions": [
    {
      "note": "S4299",
      "links": [
        {
          "url": "http://assembly.state.ny.us/leg/?sh=printbill&bn=S4299&term=2025&Text=Y",
          "media_type": "text/html"
        },
        {
          "url": "http://legislation.nysenate.gov/pdf/bills/2025/S4299",
          "media_type": "application/pdf"
        }
      ],
      "date": "",
      "classification": ""
    }
  ],
  "documents": [],
  "citations": [
    {
      "publication": "New York Laws",
      "citation": "WKC \u00a7 13-Q",
      "citation_type": "proposed",
      "effective": null,
      "expires": null,
      "url": "https://www.nysenate.gov/legislation/laws/WKC/"
    }
  ],
  "sources": [
    {
      "url": "https://legislation.nysenate.gov/api/3/bills/2025-2026/S4299?summary=&detail=",
      "note": ""
    },
    {
      "url": "http://www.nysenate.gov/legislation/bills/2025/S4299",
      "note": ""
    },
    {
      "url": "https://nyassembly.gov/leg/?bn=S04299&term=2025",
      "note": ""
    }
  ],
  "extras": {},
  "jurisdiction": {
    "id": "ocd-jurisdiction/country:us/state:ny/government",
    "name": "New York",
    "classification": "state",
    "division_id": "ocd-division/country:us/state:ny"
  },
  "scraped_at": "2025-08-05T19:24:59+00:00",
  "_id": "e036ee1e-7231-11f0-acc8-8e31291036f2"
}