{
  "legislative_session": "2025-2026",
  "identifier": "S7554",
  "title": "Allows political subdivisions which contract to receive fire protection services to jointly establish a service award program with political subdivisions which contract to receive ambulance services",
  "from_organization": "~{\"classification\": \"upper\"}",
  "classification": [
    "bill"
  ],
  "subject": [],
  "abstracts": [
    {
      "note": "",
      "abstract": "Allows political subdivisions which contract to receive fire protection services from a special fire company or department to jointly establish a service award program with political subdivisions which contract to receive ambulance services from the same special fire company or department."
    }
  ],
  "other_titles": [],
  "other_identifiers": [],
  "actions": [
    {
      "description": "REFERRED TO LOCAL GOVERNMENT",
      "date": "2025-04-22",
      "organization_id": "~{\"classification\": \"upper\"}",
      "classification": [
        "referral-committee"
      ],
      "related_entities": []
    }
  ],
  "sponsorships": [
    {
      "name": "Jack M. Martins",
      "classification": "primary",
      "entity_type": "person",
      "primary": true,
      "person_id": "~{\"name\": \"Jack M. Martins\"}",
      "organization_id": null
    }
  ],
  "related_bills": [
    {
      "identifier": "A 8224",
      "legislative_session": "2025-2026",
      "relation_type": "companion"
    },
    {
      "identifier": "A 8224",
      "legislative_session": "2025-2026",
      "relation_type": "companion"
    }
  ],
  "versions": [
    {
      "note": "S7554",
      "links": [
        {
          "url": "http://assembly.state.ny.us/leg/?sh=printbill&bn=S7554&term=2025&Text=Y",
          "media_type": "text/html"
        },
        {
          "url": "http://legislation.nysenate.gov/pdf/bills/2025/S7554",
          "media_type": "application/pdf"
        }
      ],
      "date": "",
      "classification": ""
    }
  ],
  "documents": [],
  "citations": [
    {
      "publication": "New York Laws",
      "citation": "GMU \u00a7 216-A",
      "citation_type": "proposed",
      "effective": null,
      "expires": null,
      "url": "https://www.nysenate.gov/legislation/laws/GMU/"
    }
  ],
  "sources": [
    {
      "url": "https://legislation.nysenate.gov/api/3/bills/2025-2026/S7554?summary=&detail=",
      "note": ""
    },
    {
      "url": "http://www.nysenate.gov/legislation/bills/2025/S7554",
      "note": ""
    },
    {
      "url": "https://nyassembly.gov/leg/?bn=S07554&term=2025",
      "note": ""
    }
  ],
  "extras": {},
  "jurisdiction": {
    "id": "ocd-jurisdiction/country:us/state:ny/government",
    "name": "New York",
    "classification": "state",
    "division_id": "ocd-division/country:us/state:ny"
  },
  "scraped_at": "2025-08-05T20:07:11+00:00",
  "_id": "c5dcdfbe-7237-11f0-acc8-8e31291036f2"
}