{
  "legislative_session": "2025-2026",
  "identifier": "S5357",
  "title": "Caps the monthly maximum payment for hotel rooms to house homeless persons",
  "from_organization": "~{\"classification\": \"upper\"}",
  "classification": [
    "bill"
  ],
  "subject": [],
  "abstracts": [
    {
      "note": "",
      "abstract": "Caps the monthly maximum payment for hotel rooms to house homeless persons based upon the New York city housing authority Section 8 voucher payment standards."
    }
  ],
  "other_titles": [],
  "other_identifiers": [],
  "actions": [
    {
      "description": "REFERRED TO SOCIAL SERVICES",
      "date": "2025-02-20",
      "organization_id": "~{\"classification\": \"upper\"}",
      "classification": [
        "referral-committee"
      ],
      "related_entities": []
    }
  ],
  "sponsorships": [
    {
      "name": "Leroy Comrie",
      "classification": "primary",
      "entity_type": "person",
      "primary": true,
      "person_id": "~{\"name\": \"Leroy Comrie\"}",
      "organization_id": null
    }
  ],
  "related_bills": [
    {
      "identifier": "S 9937",
      "legislative_session": "2023-2024",
      "relation_type": "prior-session"
    }
  ],
  "versions": [
    {
      "note": "S5357",
      "links": [
        {
          "url": "http://assembly.state.ny.us/leg/?sh=printbill&bn=S5357&term=2025&Text=Y",
          "media_type": "text/html"
        },
        {
          "url": "http://legislation.nysenate.gov/pdf/bills/2025/S5357",
          "media_type": "application/pdf"
        }
      ],
      "date": "",
      "classification": ""
    }
  ],
  "documents": [],
  "citations": [
    {
      "publication": "New York Laws",
      "citation": "SOS \u00a7 43-A",
      "citation_type": "proposed",
      "effective": null,
      "expires": null,
      "url": "https://www.nysenate.gov/legislation/laws/SOS/"
    }
  ],
  "sources": [
    {
      "url": "https://legislation.nysenate.gov/api/3/bills/2025-2026/S5357?summary=&detail=",
      "note": ""
    },
    {
      "url": "http://www.nysenate.gov/legislation/bills/2025/S5357",
      "note": ""
    },
    {
      "url": "https://nyassembly.gov/leg/?bn=S05357&term=2025",
      "note": ""
    }
  ],
  "extras": {},
  "jurisdiction": {
    "id": "ocd-jurisdiction/country:us/state:ny/government",
    "name": "New York",
    "classification": "state",
    "division_id": "ocd-division/country:us/state:ny"
  },
  "scraped_at": "2025-08-05T19:39:39+00:00",
  "_id": "ed02f2da-7233-11f0-acc8-8e31291036f2"
}