{"legislative_session": "2025-2026", "identifier": "S1761", "title": "Authorizes and directs the office of children and family services to conduct a study on the family assessment response program", "from_organization": "~{\"classification\": \"upper\"}", "classification": ["bill"], "subject": [], "abstracts": [{"note": "", "abstract": "Authorizes and directs the office of children and family services to conduct a study on the family assessment response program; provides for the repeal of such provisions upon expiration thereof."}], "other_titles": [], "other_identifiers": [], "actions": [{"description": "REFERRED TO CHILDREN AND FAMILIES", "date": "2025-01-13", "organization_id": "~{\"classification\": \"upper\"}", "classification": ["referral-committee"], "related_entities": []}], "sponsorships": [{"name": "Roxanne J. Persaud", "classification": "primary", "entity_type": "person", "primary": true, "person_id": "~{\"name\": \"Roxanne J. Persaud\"}", "organization_id": null}], "related_bills": [{"identifier": "A 4122", "legislative_session": "2025-2026", "relation_type": "companion"}, {"identifier": "A 4122", "legislative_session": "2025-2026", "relation_type": "companion"}, {"identifier": "S 7819", "legislative_session": "2023-2024", "relation_type": "prior-session"}, {"identifier": "S 107", "legislative_session": "2021-2022", "relation_type": "prior-session"}, {"identifier": "S 5827", "legislative_session": "2019-2020", "relation_type": "prior-session"}], "versions": [{"note": "S1761", "links": [{"url": "http://assembly.state.ny.us/leg/?sh=printbill&bn=S1761&term=2025&Text=Y", "media_type": "text/html"}, {"url": "http://legislation.nysenate.gov/pdf/bills/2025/S1761", "media_type": "application/pdf"}], "date": "", "classification": ""}], "documents": [], "citations": [], "sources": [{"url": "https://legislation.nysenate.gov/api/3/bills/2025-2026/S1761?summary=&detail=", "note": ""}, {"url": "http://www.nysenate.gov/legislation/bills/2025/S1761", "note": ""}, {"url": "https://nyassembly.gov/leg/?bn=S01761&term=2025", "note": ""}], "extras": {}, "jurisdiction": {"id": "ocd-jurisdiction/country:us/state:ny/government", "name": "New York", "classification": "state", "division_id": "ocd-division/country:us/state:ny"}, "scraped_at": "2025-08-05T18:59:23+00:00", "_id": "4cd30eda-722e-11f0-acc8-8e31291036f2"}