{"legislative_session": "2025-2026", "identifier": "S4729", "title": "Establishes the college of renewable energy and sustainability in the city university of New York", "from_organization": "~{\"classification\": \"upper\"}", "classification": ["bill"], "subject": [], "abstracts": [{"note": "", "abstract": "Establishes the college of renewable energy and sustainability in the city university of New York which shall offer majors relating to the field of renewable energy and sustainability."}], "other_titles": [], "other_identifiers": [], "actions": [{"description": "REFERRED TO HIGHER EDUCATION", "date": "2025-02-12", "organization_id": "~{\"classification\": \"upper\"}", "classification": ["referral-committee"], "related_entities": []}], "sponsorships": [{"name": "James Sanders Jr.", "classification": "primary", "entity_type": "person", "primary": true, "person_id": "~{\"name\": \"James Sanders Jr.\"}", "organization_id": null}], "related_bills": [{"identifier": "S 2004", "legislative_session": "2023-2024", "relation_type": "prior-session"}, {"identifier": "S 3176", "legislative_session": "2021-2022", "relation_type": "prior-session"}, {"identifier": "S 6099", "legislative_session": "2019-2020", "relation_type": "prior-session"}], "versions": [{"note": "S4729", "links": [{"url": "http://assembly.state.ny.us/leg/?sh=printbill&bn=S4729&term=2025&Text=Y", "media_type": "text/html"}, {"url": "http://legislation.nysenate.gov/pdf/bills/2025/S4729", "media_type": "application/pdf"}], "date": "", "classification": ""}], "documents": [], "citations": [], "sources": [{"url": "https://legislation.nysenate.gov/api/3/bills/2025-2026/S4729?summary=&detail=", "note": ""}, {"url": "http://www.nysenate.gov/legislation/bills/2025/S4729", "note": ""}, {"url": "https://nyassembly.gov/leg/?bn=S04729&term=2025", "note": ""}], "extras": {}, "jurisdiction": {"id": "ocd-jurisdiction/country:us/state:ny/government", "name": "New York", "classification": "state", "division_id": "ocd-division/country:us/state:ny"}, "scraped_at": "2025-08-05T19:31:49+00:00", "_id": "d4b2760c-7232-11f0-acc8-8e31291036f2"}