{"legislative_session": "2025-2026", "identifier": "S2410", "title": "Prohibits the acceptance of a waiver of probate form by transfer agents", "from_organization": "~{\"classification\": \"upper\"}", "classification": ["bill"], "subject": [], "abstracts": [{"note": "", "abstract": "Prohibits transfer agents from accepting waiver of probate forms to bypass formal estate procedures through the courts."}], "other_titles": [], "other_identifiers": [], "actions": [{"description": "REFERRED TO JUDICIARY", "date": "2025-01-17", "organization_id": "~{\"classification\": \"upper\"}", "classification": ["referral-committee"], "related_entities": []}], "sponsorships": [{"name": "Luis R. Sep\u00falveda", "classification": "primary", "entity_type": "person", "primary": true, "person_id": "~{\"name\": \"Luis R. Sep\\u00falveda\"}", "organization_id": null}], "related_bills": [{"identifier": "S 748", "legislative_session": "2023-2024", "relation_type": "prior-session"}, {"identifier": "S 2213", "legislative_session": "2021-2022", "relation_type": "prior-session"}, {"identifier": "S 6261", "legislative_session": "2019-2020", "relation_type": "prior-session"}], "versions": [{"note": "S2410", "links": [{"url": "http://assembly.state.ny.us/leg/?sh=printbill&bn=S2410&term=2025&Text=Y", "media_type": "text/html"}, {"url": "http://legislation.nysenate.gov/pdf/bills/2025/S2410", "media_type": "application/pdf"}], "date": "", "classification": ""}], "documents": [], "citations": [{"publication": "New York Laws", "citation": "SCP \u00a7 1409-A", "citation_type": "proposed", "effective": null, "expires": null, "url": "https://www.nysenate.gov/legislation/laws/SCP/"}], "sources": [{"url": "https://legislation.nysenate.gov/api/3/bills/2025-2026/S2410?summary=&detail=", "note": ""}, {"url": "http://www.nysenate.gov/legislation/bills/2025/S2410", "note": ""}, {"url": "https://nyassembly.gov/leg/?bn=S02410&term=2025", "note": ""}], "extras": {}, "jurisdiction": {"id": "ocd-jurisdiction/country:us/state:ny/government", "name": "New York", "classification": "state", "division_id": "ocd-division/country:us/state:ny"}, "scraped_at": "2025-08-05T19:07:21+00:00", "_id": "69b66dde-722f-11f0-acc8-8e31291036f2"}