{"legislative_session": "2025-2026", "identifier": "A4214", "title": "Relates to the contents of a notice of liability issued for a speed camera violation", "from_organization": "~{\"classification\": \"lower\"}", "classification": ["bill"], "subject": [], "abstracts": [{"note": "", "abstract": "Permits a violation captured by a speed camera to be dismissed upon the application of the person alleged to be liable for such violation if any information that is required to be inserted in the notice of liability is omitted from such notice of liability, misdescribed or illegible."}], "other_titles": [], "other_identifiers": [], "actions": [{"description": "REFERRED TO TRANSPORTATION", "date": "2025-01-31", "organization_id": "~{\"classification\": \"lower\"}", "classification": ["referral-committee"], "related_entities": []}], "sponsorships": [{"name": "Mike Reilly", "classification": "primary", "entity_type": "person", "primary": true, "person_id": "~{\"name\": \"Mike Reilly\"}", "organization_id": null}, {"name": "Michael Novakhov", "classification": "cosponsor", "entity_type": "person", "primary": false, "person_id": "~{\"name\": \"Michael Novakhov\"}", "organization_id": null}, {"name": "Joe DeStefano", "classification": "cosponsor", "entity_type": "person", "primary": false, "person_id": "~{\"name\": \"Joe DeStefano\"}", "organization_id": null}], "related_bills": [{"identifier": "S 7085", "legislative_session": "2025-2026", "relation_type": "companion"}, {"identifier": "S 7085", "legislative_session": "2025-2026", "relation_type": "companion"}, {"identifier": "A 9219", "legislative_session": "2023-2024", "relation_type": "prior-session"}, {"identifier": "S 6178", "legislative_session": "2021-2022", "relation_type": "prior-session"}, {"identifier": "S 3861", "legislative_session": "2019-2020", "relation_type": "prior-session"}, {"identifier": "S 9107", "legislative_session": "2017-2018", "relation_type": "prior-session"}], "versions": [{"note": "A4214", "links": [{"url": "http://assembly.state.ny.us/leg/?sh=printbill&bn=A4214&term=2025&Text=Y", "media_type": "text/html"}, {"url": "http://legislation.nysenate.gov/pdf/bills/2025/A4214", "media_type": "application/pdf"}], "date": "", "classification": ""}], "documents": [], "citations": [], "sources": [{"url": "https://legislation.nysenate.gov/api/3/bills/2025-2026/A4214?summary=&detail=", "note": ""}, {"url": "http://www.nysenate.gov/legislation/bills/2025/A4214", "note": ""}, {"url": "https://nyassembly.gov/leg/?bn=A04214&term=2025", "note": ""}], "extras": {}, "jurisdiction": {"id": "ocd-jurisdiction/country:us/state:ny/government", "name": "New York", "classification": "state", "division_id": "ocd-division/country:us/state:ny"}, "scraped_at": "2025-08-05T19:23:33+00:00", "_id": "acda0ef2-7231-11f0-acc8-8e31291036f2"}