{"legislative_session": "2025-2026", "identifier": "A4180", "title": "Directs the metropolitan transportation authority to provide safety briefings to passengers aboard Metro-North trains, and train personnel in safety procedures", "from_organization": "~{\"classification\": \"lower\"}", "classification": ["bill"], "subject": [], "abstracts": [{"note": "", "abstract": "Directs the metropolitan transportation authority to provide safety briefings to passengers aboard Metro-North trains, and train personnel in safety procedures."}], "other_titles": [], "other_identifiers": [], "actions": [{"description": "REFERRED TO CORPORATIONS, AUTHORITIES AND COMMISSIONS", "date": "2025-01-31", "organization_id": "~{\"classification\": \"lower\"}", "classification": ["referral-committee"], "related_entities": []}], "sponsorships": [{"name": "Alicia Hyndman", "classification": "primary", "entity_type": "person", "primary": true, "person_id": "~{\"name\": \"Alicia Hyndman\"}", "organization_id": null}], "related_bills": [{"identifier": "S 3410", "legislative_session": "2025-2026", "relation_type": "companion"}, {"identifier": "S 3410", "legislative_session": "2025-2026", "relation_type": "companion"}, {"identifier": "A 9976", "legislative_session": "2023-2024", "relation_type": "prior-session"}, {"identifier": "A 4372", "legislative_session": "2021-2022", "relation_type": "prior-session"}, {"identifier": "A 4492", "legislative_session": "2019-2020", "relation_type": "prior-session"}, {"identifier": "A 2888", "legislative_session": "2017-2018", "relation_type": "prior-session"}, {"identifier": "A 6331", "legislative_session": "2015-2016", "relation_type": "prior-session"}], "versions": [{"note": "A4180", "links": [{"url": "http://assembly.state.ny.us/leg/?sh=printbill&bn=A4180&term=2025&Text=Y", "media_type": "text/html"}, {"url": "http://legislation.nysenate.gov/pdf/bills/2025/A4180", "media_type": "application/pdf"}], "date": "", "classification": ""}], "documents": [], "citations": [], "sources": [{"url": "https://legislation.nysenate.gov/api/3/bills/2025-2026/A4180?summary=&detail=", "note": ""}, {"url": "http://www.nysenate.gov/legislation/bills/2025/A4180", "note": ""}, {"url": "https://nyassembly.gov/leg/?bn=A04180&term=2025", "note": ""}], "extras": {}, "jurisdiction": {"id": "ocd-jurisdiction/country:us/state:ny/government", "name": "New York", "classification": "state", "division_id": "ocd-division/country:us/state:ny"}, "scraped_at": "2025-08-05T19:23:13+00:00", "_id": "a1165d6e-7231-11f0-acc8-8e31291036f2"}