{"legislative_session": "2025-2026", "identifier": "S992", "title": "Relates to care and protection of children", "from_organization": "~{\"classification\": \"upper\"}", "classification": ["bill"], "subject": [], "abstracts": [{"note": "", "abstract": "Relates to care and protection of children; adds to the definition of children at risk infants who test positive for a controlled substance not prescribed by a physician, in their bloodstream or urine, are born dependent on such drugs or who demonstrate drug withdrawal symptoms, or who have been diagnosed with a condition attributable to in utero exposure to illegal drugs."}], "other_titles": [], "other_identifiers": [], "actions": [{"description": "REFERRED TO DISABILITIES", "date": "2025-01-08", "organization_id": "~{\"classification\": \"upper\"}", "classification": ["referral-committee"], "related_entities": []}], "sponsorships": [{"name": "Robert Rolison", "classification": "primary", "entity_type": "person", "primary": true, "person_id": "~{\"name\": \"Robert Rolison\"}", "organization_id": null}], "related_bills": [{"identifier": "S 8179", "legislative_session": "2023-2024", "relation_type": "prior-session"}], "versions": [{"note": "S992", "links": [{"url": "http://assembly.state.ny.us/leg/?sh=printbill&bn=S992&term=2025&Text=Y", "media_type": "text/html"}, {"url": "http://legislation.nysenate.gov/pdf/bills/2025/S992", "media_type": "application/pdf"}], "date": "", "classification": ""}], "documents": [], "citations": [{"publication": "New York Laws", "citation": "FCT \u00a7 1012", "citation_type": "proposed", "effective": null, "expires": null, "url": "https://www.nysenate.gov/legislation/laws/FCT/"}, {"publication": "New York Laws", "citation": "PBH \u00a7 2541", "citation_type": "proposed", "effective": null, "expires": null, "url": "https://www.nysenate.gov/legislation/laws/PBH/"}, {"publication": "New York Laws", "citation": "PBH \u00a7 2542", "citation_type": "proposed", "effective": null, "expires": null, "url": "https://www.nysenate.gov/legislation/laws/PBH/"}, {"publication": "New York Laws", "citation": "SOS \u00a7 371", "citation_type": "proposed", "effective": null, "expires": null, "url": "https://www.nysenate.gov/legislation/laws/SOS/"}], "sources": [{"url": "https://legislation.nysenate.gov/api/3/bills/2025-2026/S992?summary=&detail=", "note": ""}, {"url": "http://www.nysenate.gov/legislation/bills/2025/S992", "note": ""}, {"url": "https://nyassembly.gov/leg/?bn=S00992&term=2025", "note": ""}], "extras": {}, "jurisdiction": {"id": "ocd-jurisdiction/country:us/state:ny/government", "name": "New York", "classification": "state", "division_id": "ocd-division/country:us/state:ny"}, "scraped_at": "2025-08-05T18:49:52+00:00", "_id": "f889dc74-722c-11f0-acc8-8e31291036f2"}