{"legislative_session": "2025-2026", "identifier": "S5921", "title": "Provides that either a person or an unborn child in any stage of gestation may be the victim of an assault", "from_organization": "~{\"classification\": \"upper\"}", "classification": ["bill"], "subject": [], "abstracts": [{"note": "", "abstract": "Provides that either a person or an unborn child in any stage of gestation may be the victim of an assault or homicide; states situations when it does not constitute an assault on an unborn child such as during the course of an otherwise lawful abortion, during normal medical treatment or by the pregnant woman; defines \"person\" to include any human being who is born and is alive or an unborn child at any stage of gestation."}], "other_titles": [], "other_identifiers": [], "actions": [{"description": "REFERRED TO CODES", "date": "2025-03-04", "organization_id": "~{\"classification\": \"upper\"}", "classification": ["referral-committee"], "related_entities": []}], "sponsorships": [{"name": "Alexis Weik", "classification": "primary", "entity_type": "person", "primary": true, "person_id": "~{\"name\": \"Alexis Weik\"}", "organization_id": null}], "related_bills": [{"identifier": "S 5308", "legislative_session": "2023-2024", "relation_type": "prior-session"}, {"identifier": "S 2669", "legislative_session": "2021-2022", "relation_type": "prior-session"}, {"identifier": "S 1383", "legislative_session": "2019-2020", "relation_type": "prior-session"}, {"identifier": "S 3830", "legislative_session": "2017-2018", "relation_type": "prior-session"}, {"identifier": "S 2532", "legislative_session": "2015-2016", "relation_type": "prior-session"}, {"identifier": "S 1950", "legislative_session": "2013-2014", "relation_type": "prior-session"}, {"identifier": "S 4347", "legislative_session": "2011-2012", "relation_type": "prior-session"}, {"identifier": "S 4897", "legislative_session": "2009-2010", "relation_type": "prior-session"}, {"identifier": "S 3117", "legislative_session": "2007-2008", "relation_type": "prior-session"}], "versions": [{"note": "S5921", "links": [{"url": "http://assembly.state.ny.us/leg/?sh=printbill&bn=S5921&term=2025&Text=Y", "media_type": "text/html"}, {"url": "http://legislation.nysenate.gov/pdf/bills/2025/S5921", "media_type": "application/pdf"}], "date": "", "classification": ""}], "documents": [], "citations": [{"publication": "New York Laws", "citation": "PEN \u00a7 120.75", "citation_type": "proposed", "effective": null, "expires": null, "url": "https://www.nysenate.gov/legislation/laws/PEN/"}, {"publication": "New York Laws", "citation": "PEN \u00a7 120.80", "citation_type": "proposed", "effective": null, "expires": null, "url": "https://www.nysenate.gov/legislation/laws/PEN/"}, {"publication": "New York Laws", "citation": "PEN \u00a7 125.00", "citation_type": "proposed", "effective": null, "expires": null, "url": "https://www.nysenate.gov/legislation/laws/PEN/"}, {"publication": "New York Laws", "citation": "PEN \u00a7 125.05", "citation_type": "proposed", "effective": null, "expires": null, "url": "https://www.nysenate.gov/legislation/laws/PEN/"}], "sources": [{"url": "https://legislation.nysenate.gov/api/3/bills/2025-2026/S5921?summary=&detail=", "note": ""}, {"url": "http://www.nysenate.gov/legislation/bills/2025/S5921", "note": ""}, {"url": "https://nyassembly.gov/leg/?bn=S05921&term=2025", "note": ""}], "extras": {}, "jurisdiction": {"id": "ocd-jurisdiction/country:us/state:ny/government", "name": "New York", "classification": "state", "division_id": "ocd-division/country:us/state:ny"}, "scraped_at": "2025-08-05T19:45:42+00:00", "_id": "c55eb290-7234-11f0-acc8-8e31291036f2"}