{
  "legislative_session": "2025-2026",
  "identifier": "A745",
  "title": "Eliminates rent for homeless shelters; repealer",
  "from_organization": "~{\"classification\": \"lower\"}",
  "classification": [
    "bill"
  ],
  "subject": [],
  "abstracts": [
    {
      "note": "",
      "abstract": "Relates to eliminating rent for homeless shelters; provides that a homeless individual or family applying for or receiving temporary housing assistance shall not be required to pay to any local or state government or agency or any provider, room and board or contribute any earned or unearned income, available benefits or resources to eliminate their need for temporary housing assistance or as a condition to receive temporary housing assistance from such provider."
    }
  ],
  "other_titles": [],
  "other_identifiers": [],
  "actions": [
    {
      "description": "REFERRED TO SOCIAL SERVICES",
      "date": "2025-01-08",
      "organization_id": "~{\"classification\": \"lower\"}",
      "classification": [
        "referral-committee"
      ],
      "related_entities": []
    }
  ],
  "sponsorships": [
    {
      "name": "Andrew Hevesi",
      "classification": "primary",
      "entity_type": "person",
      "primary": true,
      "person_id": "~{\"name\": \"Andrew Hevesi\"}",
      "organization_id": null
    },
    {
      "name": "Charles Lavine",
      "classification": "cosponsor",
      "entity_type": "person",
      "primary": false,
      "person_id": "~{\"name\": \"Charles Lavine\"}",
      "organization_id": null
    },
    {
      "name": "Catalina Cruz",
      "classification": "cosponsor",
      "entity_type": "person",
      "primary": false,
      "person_id": "~{\"name\": \"Catalina Cruz\"}",
      "organization_id": null
    },
    {
      "name": "Jo Anne Simon",
      "classification": "cosponsor",
      "entity_type": "person",
      "primary": false,
      "person_id": "~{\"name\": \"Jo Anne Simon\"}",
      "organization_id": null
    },
    {
      "name": "Pamela J. Hunter",
      "classification": "cosponsor",
      "entity_type": "person",
      "primary": false,
      "person_id": "~{\"name\": \"Pamela J. Hunter\"}",
      "organization_id": null
    },
    {
      "name": "Harvey Epstein",
      "classification": "cosponsor",
      "entity_type": "person",
      "primary": false,
      "person_id": "~{\"name\": \"Harvey Epstein\"}",
      "organization_id": null
    },
    {
      "name": "Phara Souffrant Forrest",
      "classification": "cosponsor",
      "entity_type": "person",
      "primary": false,
      "person_id": "~{\"name\": \"Phara Souffrant Forrest\"}",
      "organization_id": null
    },
    {
      "name": "Amy Paulin",
      "classification": "cosponsor",
      "entity_type": "person",
      "primary": false,
      "person_id": "~{\"name\": \"Amy Paulin\"}",
      "organization_id": null
    },
    {
      "name": "Linda Rosenthal",
      "classification": "cosponsor",
      "entity_type": "person",
      "primary": false,
      "person_id": "~{\"name\": \"Linda Rosenthal\"}",
      "organization_id": null
    },
    {
      "name": "Matthew Slater",
      "classification": "cosponsor",
      "entity_type": "person",
      "primary": false,
      "person_id": "~{\"name\": \"Matthew Slater\"}",
      "organization_id": null
    },
    {
      "name": "Manny De Los Santos",
      "classification": "cosponsor",
      "entity_type": "person",
      "primary": false,
      "person_id": "~{\"name\": \"Manny De Los Santos\"}",
      "organization_id": null
    },
    {
      "name": "Chris Burdick",
      "classification": "cosponsor",
      "entity_type": "person",
      "primary": false,
      "person_id": "~{\"name\": \"Chris Burdick\"}",
      "organization_id": null
    },
    {
      "name": "Dana Levenberg",
      "classification": "cosponsor",
      "entity_type": "person",
      "primary": false,
      "person_id": "~{\"name\": \"Dana Levenberg\"}",
      "organization_id": null
    }
  ],
  "related_bills": [
    {
      "identifier": "S 3787",
      "legislative_session": "2025-2026",
      "relation_type": "companion"
    },
    {
      "identifier": "S 3787",
      "legislative_session": "2025-2026",
      "relation_type": "companion"
    },
    {
      "identifier": "A 2454",
      "legislative_session": "2023-2024",
      "relation_type": "prior-session"
    },
    {
      "identifier": "A 2585",
      "legislative_session": "2021-2022",
      "relation_type": "prior-session"
    },
    {
      "identifier": "A 7612",
      "legislative_session": "2019-2020",
      "relation_type": "prior-session"
    }
  ],
  "versions": [
    {
      "note": "A745",
      "links": [
        {
          "url": "http://assembly.state.ny.us/leg/?sh=printbill&bn=A745&term=2025&Text=Y",
          "media_type": "text/html"
        },
        {
          "url": "http://legislation.nysenate.gov/pdf/bills/2025/A745",
          "media_type": "application/pdf"
        }
      ],
      "date": "",
      "classification": ""
    }
  ],
  "documents": [],
  "citations": [],
  "sources": [
    {
      "url": "https://legislation.nysenate.gov/api/3/bills/2025-2026/A745?summary=&detail=",
      "note": ""
    },
    {
      "url": "http://www.nysenate.gov/legislation/bills/2025/A745",
      "note": ""
    },
    {
      "url": "https://nyassembly.gov/leg/?bn=A00745&term=2025",
      "note": ""
    }
  ],
  "extras": {},
  "jurisdiction": {
    "id": "ocd-jurisdiction/country:us/state:ny/government",
    "name": "New York",
    "classification": "state",
    "division_id": "ocd-division/country:us/state:ny"
  },
  "scraped_at": "2025-08-05T18:48:17+00:00",
  "_id": "bfa18916-722c-11f0-acc8-8e31291036f2"
}