{
  "legislative_session": "2025-2026",
  "identifier": "A2342",
  "title": "Provides for service of parking tickets by mail",
  "from_organization": "~{\"classification\": \"lower\"}",
  "classification": [
    "bill"
  ],
  "subject": [],
  "abstracts": [
    {
      "note": "",
      "abstract": "Provides for service of parking tickets by mail; provides additional time to respond to a parking ticket so served."
    }
  ],
  "other_titles": [],
  "other_identifiers": [],
  "actions": [
    {
      "description": "REFERRED TO TRANSPORTATION",
      "date": "2025-01-16",
      "organization_id": "~{\"classification\": \"lower\"}",
      "classification": [
        "referral-committee"
      ],
      "related_entities": []
    },
    {
      "description": "AMEND AND RECOMMIT TO TRANSPORTATION",
      "date": "2025-05-15",
      "organization_id": "~{\"classification\": \"lower\"}",
      "classification": [
        "amendment-passage",
        "referral-committee"
      ],
      "related_entities": []
    },
    {
      "description": "PRINT NUMBER 2342A",
      "date": "2025-05-15",
      "organization_id": "~{\"classification\": \"lower\"}",
      "classification": [
        "amendment-passage"
      ],
      "related_entities": []
    }
  ],
  "sponsorships": [
    {
      "name": "Carrie Woerner",
      "classification": "primary",
      "entity_type": "person",
      "primary": true,
      "person_id": "~{\"name\": \"Carrie Woerner\"}",
      "organization_id": null
    },
    {
      "name": "Manny De Los Santos",
      "classification": "cosponsor",
      "entity_type": "person",
      "primary": false,
      "person_id": "~{\"name\": \"Manny De Los Santos\"}",
      "organization_id": null
    }
  ],
  "related_bills": [
    {
      "identifier": "S 2108",
      "legislative_session": "2025-2026",
      "relation_type": "companion"
    },
    {
      "identifier": "S 2108",
      "legislative_session": "2025-2026",
      "relation_type": "companion"
    },
    {
      "identifier": "S 2108",
      "legislative_session": "2025-2026",
      "relation_type": "companion"
    },
    {
      "identifier": "A 10228",
      "legislative_session": "2023-2024",
      "relation_type": "prior-session"
    }
  ],
  "versions": [
    {
      "note": "A2342",
      "links": [
        {
          "url": "http://assembly.state.ny.us/leg/?sh=printbill&bn=A2342&term=2025&Text=Y",
          "media_type": "text/html"
        },
        {
          "url": "http://legislation.nysenate.gov/pdf/bills/2025/A2342",
          "media_type": "application/pdf"
        }
      ],
      "date": "",
      "classification": ""
    },
    {
      "note": "A2342A",
      "links": [
        {
          "url": "http://legislation.nysenate.gov/pdf/bills/2025/A2342A",
          "media_type": "application/pdf"
        }
      ],
      "date": "",
      "classification": ""
    }
  ],
  "documents": [],
  "citations": [
    {
      "publication": "New York Laws",
      "citation": "VAT \u00a7 238",
      "citation_type": "proposed",
      "effective": null,
      "expires": null,
      "url": "https://www.nysenate.gov/legislation/laws/VAT/"
    }
  ],
  "sources": [
    {
      "url": "https://legislation.nysenate.gov/api/3/bills/2025-2026/A2342?summary=&detail=",
      "note": ""
    },
    {
      "url": "http://www.nysenate.gov/legislation/bills/2025/A2342",
      "note": ""
    },
    {
      "url": "https://nyassembly.gov/leg/?bn=A02342&term=2025",
      "note": ""
    }
  ],
  "extras": {},
  "jurisdiction": {
    "id": "ocd-jurisdiction/country:us/state:ny/government",
    "name": "New York",
    "classification": "state",
    "division_id": "ocd-division/country:us/state:ny"
  },
  "scraped_at": "2025-08-05T19:05:54+00:00",
  "_id": "35f3f462-722f-11f0-acc8-8e31291036f2"
}