{
  "legislative_session": "2025-2026",
  "identifier": "A770",
  "title": "Requires school districts to adopt a policy prohibiting the use of cellular telephones during classroom instruction",
  "from_organization": "~{\"classification\": \"lower\"}",
  "classification": [
    "bill"
  ],
  "subject": [],
  "abstracts": [
    {
      "note": "",
      "abstract": "Requires school districts to adopt a policy prohibiting the use of cellular telephones during classroom instruction; requires the department of education to adopt a model policy for use by school districts."
    }
  ],
  "other_titles": [],
  "other_identifiers": [],
  "actions": [
    {
      "description": "REFERRED TO EDUCATION",
      "date": "2025-01-08",
      "organization_id": "~{\"classification\": \"lower\"}",
      "classification": [
        "referral-committee"
      ],
      "related_entities": []
    }
  ],
  "sponsorships": [
    {
      "name": "Harvey Epstein",
      "classification": "primary",
      "entity_type": "person",
      "primary": true,
      "person_id": "~{\"name\": \"Harvey Epstein\"}",
      "organization_id": null
    }
  ],
  "related_bills": [],
  "versions": [
    {
      "note": "A770",
      "links": [
        {
          "url": "http://assembly.state.ny.us/leg/?sh=printbill&bn=A770&term=2025&Text=Y",
          "media_type": "text/html"
        },
        {
          "url": "http://legislation.nysenate.gov/pdf/bills/2025/A770",
          "media_type": "application/pdf"
        }
      ],
      "date": "",
      "classification": ""
    }
  ],
  "documents": [],
  "citations": [
    {
      "publication": "New York Laws",
      "citation": "EDN \u00a7 2801-C",
      "citation_type": "proposed",
      "effective": null,
      "expires": null,
      "url": "https://www.nysenate.gov/legislation/laws/EDN/"
    }
  ],
  "sources": [
    {
      "url": "https://legislation.nysenate.gov/api/3/bills/2025-2026/A770?summary=&detail=",
      "note": ""
    },
    {
      "url": "http://www.nysenate.gov/legislation/bills/2025/A770",
      "note": ""
    },
    {
      "url": "https://nyassembly.gov/leg/?bn=A00770&term=2025",
      "note": ""
    }
  ],
  "extras": {},
  "jurisdiction": {
    "id": "ocd-jurisdiction/country:us/state:ny/government",
    "name": "New York",
    "classification": "state",
    "division_id": "ocd-division/country:us/state:ny"
  },
  "scraped_at": "2025-08-05T18:48:41+00:00",
  "_id": "ce4e737a-722c-11f0-acc8-8e31291036f2"
}