{
  "legislative_session": "2025-2026",
  "identifier": "S4366",
  "title": "Relates to awards of certain contracts to small businesses or businesses certified under article 15-A of the executive law",
  "from_organization": "~{\"classification\": \"upper\"}",
  "classification": [
    "bill"
  ],
  "subject": [],
  "abstracts": [
    {
      "note": "",
      "abstract": "Relates to awards of certain contracts to small businesses or businesses certified under article 15-A of the executive law."
    }
  ],
  "other_titles": [],
  "other_identifiers": [],
  "actions": [
    {
      "description": "REFERRED TO CORPORATIONS, AUTHORITIES AND COMMISSIONS",
      "date": "2025-02-04",
      "organization_id": "~{\"classification\": \"upper\"}",
      "classification": [
        "referral-committee"
      ],
      "related_entities": []
    }
  ],
  "sponsorships": [
    {
      "name": "Leroy Comrie",
      "classification": "primary",
      "entity_type": "person",
      "primary": true,
      "person_id": "~{\"name\": \"Leroy Comrie\"}",
      "organization_id": null
    }
  ],
  "related_bills": [
    {
      "identifier": "A 4351",
      "legislative_session": "2025-2026",
      "relation_type": "companion"
    },
    {
      "identifier": "A 4351",
      "legislative_session": "2025-2026",
      "relation_type": "companion"
    },
    {
      "identifier": "S 3019",
      "legislative_session": "2023-2024",
      "relation_type": "prior-session"
    },
    {
      "identifier": "S 5851",
      "legislative_session": "2021-2022",
      "relation_type": "prior-session"
    },
    {
      "identifier": "S 1869",
      "legislative_session": "2019-2020",
      "relation_type": "prior-session"
    }
  ],
  "versions": [
    {
      "note": "S4366",
      "links": [
        {
          "url": "http://assembly.state.ny.us/leg/?sh=printbill&bn=S4366&term=2025&Text=Y",
          "media_type": "text/html"
        },
        {
          "url": "http://legislation.nysenate.gov/pdf/bills/2025/S4366",
          "media_type": "application/pdf"
        }
      ],
      "date": "",
      "classification": ""
    }
  ],
  "documents": [],
  "citations": [
    {
      "publication": "New York Laws",
      "citation": "PBA \u00a7 1678",
      "citation_type": "proposed",
      "effective": null,
      "expires": null,
      "url": "https://www.nysenate.gov/legislation/laws/PBA/"
    }
  ],
  "sources": [
    {
      "url": "https://legislation.nysenate.gov/api/3/bills/2025-2026/S4366?summary=&detail=",
      "note": ""
    },
    {
      "url": "http://www.nysenate.gov/legislation/bills/2025/S4366",
      "note": ""
    },
    {
      "url": "https://nyassembly.gov/leg/?bn=S04366&term=2025",
      "note": ""
    }
  ],
  "extras": {},
  "jurisdiction": {
    "id": "ocd-jurisdiction/country:us/state:ny/government",
    "name": "New York",
    "classification": "state",
    "division_id": "ocd-division/country:us/state:ny"
  },
  "scraped_at": "2025-08-05T19:26:41+00:00",
  "_id": "1d6d9cd8-7232-11f0-acc8-8e31291036f2"
}