{
  "legislative_session": "2025-2026",
  "identifier": "A7383",
  "title": "Allows Andriel Santana to be eligible to take the civil service exam for the position of Columbia county deputy sheriff",
  "from_organization": "~{\"classification\": \"lower\"}",
  "classification": [
    "bill"
  ],
  "subject": [],
  "abstracts": [
    {
      "note": "",
      "abstract": "Allows Andriel Santana to be eligible to take the civil service exam for the position of Columbia county deputy sheriff."
    }
  ],
  "other_titles": [],
  "other_identifiers": [],
  "actions": [
    {
      "description": "REFERRED TO GOVERNMENTAL EMPLOYEES",
      "date": "2025-03-25",
      "organization_id": "~{\"classification\": \"lower\"}",
      "classification": [
        "referral-committee"
      ],
      "related_entities": []
    }
  ],
  "sponsorships": [
    {
      "name": "Didi Barrett",
      "classification": "primary",
      "entity_type": "person",
      "primary": true,
      "person_id": "~{\"name\": \"Didi Barrett\"}",
      "organization_id": null
    }
  ],
  "related_bills": [
    {
      "identifier": "S 6820",
      "legislative_session": "2025-2026",
      "relation_type": "companion"
    },
    {
      "identifier": "S 6820",
      "legislative_session": "2025-2026",
      "relation_type": "companion"
    }
  ],
  "versions": [
    {
      "note": "A7383",
      "links": [
        {
          "url": "http://assembly.state.ny.us/leg/?sh=printbill&bn=A7383&term=2025&Text=Y",
          "media_type": "text/html"
        },
        {
          "url": "http://legislation.nysenate.gov/pdf/bills/2025/A7383",
          "media_type": "application/pdf"
        }
      ],
      "date": "",
      "classification": ""
    }
  ],
  "documents": [],
  "citations": [],
  "sources": [
    {
      "url": "https://legislation.nysenate.gov/api/3/bills/2025-2026/A7383?summary=&detail=",
      "note": ""
    },
    {
      "url": "http://www.nysenate.gov/legislation/bills/2025/A7383",
      "note": ""
    },
    {
      "url": "https://nyassembly.gov/leg/?bn=A07383&term=2025",
      "note": ""
    }
  ],
  "extras": {},
  "jurisdiction": {
    "id": "ocd-jurisdiction/country:us/state:ny/government",
    "name": "New York",
    "classification": "state",
    "division_id": "ocd-division/country:us/state:ny"
  },
  "scraped_at": "2025-08-05T19:58:03+00:00",
  "_id": "7ebfa50e-7236-11f0-acc8-8e31291036f2"
}